Lab_01/post lab/design.v
module post_lab(A,B,C,D,Q);

    input A,B,C,D;
    output Q;
    assign Q = (A|(!(C|D)))^((B^D)|(B&C));

endmodule

Lab_01/post lab/testbench.v
module tb();

    reg A,B,C,D;
    wire Q;

    post_lab dut(.A(A),.B(B),.C(C),.D(D),.Q(Q));

    initial begin
        A <= 1'b0;
        B <= 1'b0;
        C <= 1'b0;
        D <= 1'b0;
        #100;

        A <= 1'b0;
        B <= 1'b0;
        C <= 1'b0;
        D <= 1'b1;
        #100;

        A <= 1'b0;
        B <= 1'b0;
        C <= 1'b1;
        D <= 1'b0;
        #100;

        A <= 1'b0;
        B <= 1'b0;
        C <= 1'b1;
        D <= 1'b1;
        #100;

        A <= 1'b0;
        B <= 1'b1;
        C <= 1'b0;
        D <= 1'b0;
        #100;

        A <= 1'b0;
        B <= 1'b1;
        C <= 1'b0;
        D <= 1'b1;
        #100;

        A <= 1'b0;
        B <= 1'b1;
        C <= 1'b1;
        D <= 1'b0;
        #100;

        A <= 1'b0;
        B <= 1'b1;
        C <= 1'b1;
        D <= 1'b1;
        #100;

        A <= 1'b1;
        B <= 1'b0;
        C <= 1'b0;
        D <= 1'b0;
        #100;

        A <= 1'b1;
        B <= 1'b0;
        C <= 1'b0;
        D <= 1'b1;
        #100;

        A <= 1'b1;
        B <= 1'b0;
        C <= 1'b1;
        D <= 1'b0;
        #100;

        A <= 1'b1;
        B <= 1'b0;
        C <= 1'b1;
        D <= 1'b1;
        #100;

        A <= 1'b1;
        B <= 1'b1;
        C <= 1'b0;
        D <= 1'b0;
        #100;

        A <= 1'b1;
        B <= 1'b1;
        C <= 1'b0;
        D <= 1'b1;
        #100;

        A <= 1'b1;
        B <= 1'b1;
        C <= 1'b1;
        D <= 1'b0;
        #100;

        A <= 1'b1;
        B <= 1'b1;
        C <= 1'b1;
        D <= 1'b1;
        #100;
        $finish;
    end

    initial begin
        $dumpfile("dump.vcd");
        $dumpvars(0);
    end

endmodule

Lab_01/post lab/dump.vcd
$date
	Sat Nov 05 16:30:06 2022
$end
$version
	Icarus Verilog
$end
$timescale
	1s
$end
$scope module tb $end
$var wire 1 ! Q $end
$var reg 1 " A $end
$var reg 1 # B $end
$var reg 1 $ C $end
$var reg 1 % D $end
$scope module dut $end
$var wire 1 " A $end
$var wire 1 # B $end
$var wire 1 $ C $end
$var wire 1 % D $end
$var wire 1 ! Q $end
$upscope $end
$upscope $end
$enddefinitions $end
$comment Show the parameter values. $end
$dumpall
$end
#0
$dumpvars
0%
0$
0#
0"
1!
$end
#100
1%
#200
0!
0%
1$
#300
1!
1%
#400
0!
0%
0$
1#
#500
1%
#600
1!
0%
1$
#700
1%
#800
1!
0%
0$
0#
1"
#900
0!
1%
#1000
1!
0%
1$
#1100
0!
1%
#1200
0%
0$
1#
#1300
1!
1%
#1400
0!
0%
1$
#1500
1%
