Lab_02/sequential circuit/design.v
module combinational_circuit(A,B,C,clk,reset,Q);

    input A,B,C,clk,reset;
    output Q;

    // interim signals
    wire A_xor_B , A_and_B , A_or_B_C;
    reg flop;

    // logic designing
    assign A_xor_B = A ^ B;
    assign A_and_B = A & B;
    assign A_or_B_C = C | A_and_B | A_xor_B;

    always @(posedge clk) begin
        if(reset == 1'b1)
        begin
            flop <= 1'b0;
        end
        else begin
            flop <= A_or_B_C;
        end
    end

    assign Q = flop;

endmodule

// assign = (A ^ B) | (A & B) | C;

Lab_02/sequential circuit/testbench.v
module tb();

    reg A,B,C,clk,reset;
    wire Q;
    // module declare
    combinational_circuit dut (.A(A),.B(B),.C(C),.clk(clk),.reset(reset),.Q(Q));

    always begin 
      clk <= 1'b0;
      #50;
      clk <= 1'b1;
    end

    initial begin
      reset <= 1'b1;
      #100;
      reset <= 1'b0;
      A <= 1'b0;
      B <= 1'b0;
      C <= 1'b0;
      #100;

      A <= 1'b0;
      B <= 1'b0;
      C <= 1'b1;
      #100;

      A <= 1'b0;
      B <= 1'b1;
      C <= 1'b0;
      #100;

      A <= 1'b0;
      B <= 1'b1;
      C <= 1'b1;
      #100;

      A <= 1'b1;
      B <= 1'b0;
      C <= 1'b0;
      #100;

      A <= 1'b1;
      B <= 1'b0;
      C <= 1'b1;
      #100;

      A <= 1'b1;
      B <= 1'b1;
      C <= 1'b0;
      #100;

      A <= 1'b1;
      B <= 1'b1;
      C <= 1'b1;
      #100;
      $finish;
    end

    initial begin
        $dumpfile("dump.vcd");
        $dumpvars(0);
    end

endmodule

Lab_02/sequential circuit/dump.vcd
$date
	Tue Nov 01 09:52:58 2022
$end
$version
	Icarus Verilog
$end
$timescale
	1s
$end
$scope module tb $end
$var wire 1 ! Q $end
$var reg 1 " A $end
$var reg 1 # B $end
$var reg 1 $ C $end
$var reg 1 % clk $end
$var reg 1 & reset $end
$scope module dut $end
$var wire 1 " A $end
$var wire 1 ' A_and_B $end
$var wire 1 ( A_or_B_C $end
$var wire 1 ) A_xor_B $end
$var wire 1 # B $end
$var wire 1 $ C $end
$var wire 1 ! Q $end
$var wire 1 % clk $end
$var wire 1 & reset $end
$var reg 1 * flop $end
$upscope $end
$upscope $end
$enddefinitions $end
$comment Show the parameter values. $end
$dumpall
$end
#0
$dumpvars
x*
x)
x(
x'
1&
0%
x$
x#
x"
x!
$end
#50
0!
0*
0%
#100
x!
x*
0(
0)
0'
0%
0$
0#
0"
0&
#150
0!
0*
0%
#200
1(
0%
1$
#250
1!
1*
0%
#300
1)
0%
0$
1#
#350
0%
#400
0%
1$
#450
0%
#500
0%
0$
0#
1"
#550
0%
#600
0%
1$
#650
0%
#700
0)
1'
0%
0$
1#
#750
0%
#800
0%
1$
