lab-07/adder/design.v
module Adder(Inp1,Inp2,Sum);

    input [31:0] Inp1,Inp2;
    output [31:0]Sum;

    assign Sum = Inp1+Inp2;

endmodule

lab-07/data-memory/design.v
module data_memory(clk,A,WD,WE,RD,reset);

    input[31:0] A,WD;
    input WE,clk,reset;
    output [31:0] RD;

    reg[31:0] memory [1023:0];

    initial begin
        memory[0] <= 32'h00000005;
        memory[1] <= 32'h00000007;
        memory[2] <= 32'h00000009;
        memory[3] <= 32'h0000000A;
    end

    assign RD = (WE == 1'b0) ? memory[A] : 32'h00000000;

    always@(posedge clk) begin
        if(WE == 1'b1) begin
            memory[A] <=  WD;
        end
    end

endmodule

Lab-09/ALU/design.v
module Flags_ALU(A, B, ctrl, Result, Z, N, C, V);

  // inputs
  input [31:0] A, B;
  input [2:0] ctrl;

  // outputs
  output [31:0] Result;
  // Flags for Zero, Negative, Carry and Overflow respectively.
  output Z,N,C,V;

  // interim wires
  wire [31:0] A_and_B, A_or_B, B_not, A_sum_B;
  wire [31:0] S1;
  wire [31:0] not_Result;
  wire Cout, xor_A_Sum, xnor_A_B_ctrl0, ctrl1_not;

  // Logic Designing
  // And
  assign A_and_B = A & B;
  // Or
  assign A_or_B = A | B;
  // Not
  assign B_not = ~B;
  // 2x1 Mux for addition or subtraction
  assign S1 = (ctrl[0] == 1'b1) ? B_not : B;
  // Addition / Subtraction
  assign {Cout, A_sum_B} = A + S1 + ctrl[0];
  // Result output through 4x1 Mux
  assign Result = (ctrl[1:0] == 2'b00) ? A_sum_B :
                  (ctrl[1:0] == 2'b01) ? A_sum_B :
                  (ctrl[1:0] == 2'b10) ? A_and_B : A_or_B;

  // Flags Outputs
  // for zero checking
  assign not_Result = ~Result;
  assign Z = &(not_Result);
  // for negative checking
  assign N = Result[31];
  //for carry checking
  assign ctrl1_not = (~ctrl[1]);
  assign C = ctrl1_not & Cout;
  // for overflow checking
  assign xor_A_Sum = A_sum_B[31] ^ A[31];
  assign xnor_A_B_ctrl0 = ~(A[31] ^ B[31] ^ ctrl[0]);
  assign V = ctrl1_not & xor_A_Sum & xnor_A_B_ctrl0;

endmodule

lab-07/sign-extension/design.v
module sign_extension(Imm,ImmExt);

    input [11:0] Imm;
    output [31:0] ImmExt;

    assign ImmExt = {{20{Imm[11]}},Imm};

endmodule

lab-07/register-file/design.v
module register_file(A1,A2,A3,clk,reset,RD1,RD2,WD3,WE3);

    input[4:0] A1,A2,A3;
    input clk,reset,WE3;
    input[31:0] WD3;
    output [31:0]RD1,RD2;
    reg[31:0] register[31:0];
    
    initial begin
        register[0] <= 32'h00000000;
        register[1] <= 32'h00000000;
        register[2] <= 32'h00000000;
        register[3] <= 32'h00000000;
        register[4] <= 32'h00000000;
        register[5] <= 32'h00000000;
        register[6] <= 32'h00000000;
        register[7] <= 32'h00000000;
        register[8] <= 32'h00000000;
        register[9] <= 32'h00000000;
        register[10] <= 32'h00000000;
        register[11] <= 32'h00000000;
        register[12] <= 32'h00000000;
        register[13] <= 32'h00000000;
        register[14] <= 32'h00000000;
        register[15] <= 32'h00000000;
    end

    assign RD1 = (reset == 1'b1) ? 32'd0 : register[A1];
    assign RD2 = (reset == 1'b1) ? 32'd0 : register[A2];

    always@ (negedge clk) begin
        if((WE3 == 1'b1) & (A3 != 5'h00)) begin
            register[A3] <= WD3;
            
        end
    end


endmodule

Lab-09/alu_decoder.v
module alu_decoder(ALUOp, func3, op5, func7_5, ALUControl);
    input [1:0] ALUOp;
    input [2:0] func3;
    input op5, func7_5;
    wire [1:0] signal;

    output [2:0] ALUControl;

    assign signal = {op5, func7_5};

    assign ALUControl = (ALUOp == 2'b00) ? 3'b000 :
                        (ALUOp == 2'b01) ? 3'b001 :
                        ((ALUOp == 2'b10) & (func3 == 3'b000) & (signal == 2'b11)) ? 3'b001 :
                        ((ALUOp == 2'b10) & (func3 == 3'b000) & (signal != 2'b11)) ? 3'b000 :
                        ((ALUOp == 2'b10) & (func3 == 3'b010)) ? 3'b101 :
                        ((ALUOp == 2'b10) & (func3 == 3'b110)) ? 3'b011 :
                        ((ALUOp == 2'b10) & (func3 == 3'b011)) ? 3'b010 : 3'b000;

endmodule

Lab-09/main_decoder.v
module main_decoder(op, RegWrite, ALUSrc, MemWrite, ResultSrc, Branch, ImmSrc, ALUOp);

    input[6:0] op;
    output RegWrite, ALUSrc, MemWrite, ResultSrc, Branch;
    output [1:0] ImmSrc, ALUOp;

    assign RegWrite = ((op == 7'b0000011) | (op == 7'b0110011)) ? 1'b1 : 1'b0;
    assign ALUSrc = ((op == 7'b0000011) | (op == 7'b0100011)) ? 1'b1 : 1'b0;
    assign MemWrite = ((op == 7'b0100011)) ? 1'b1 : 1'b0;
    assign ResultSrc = ((op == 7'b0000011)) ? 1'b1 : 1'b0;
    assign Branch = ((op == 7'b1100011)) ? 1'b1 : 1'b0;

    assign ImmSrc = ((op == 7'b0100011)) ? 2'b01 : (op == 7'b1100011) ? 2'b10 : 2'b00;
    assign ALUOp = ((op == 7'b0110011)) ? 2'b10 : (op == 7'b1100011) ? 2'b01 : 2'b00;

endmodule

lab-05_2/ControlUnit/control_unit.v

module control_unit(zero, op, func3, func7, PCSrc, RegWrite, ALUSrc, MemWrite, ResultSrc, ImmSrc, ALUControl);

    input zero, func7;
    input [6:0] op;
    input [2:0] func3;

    output PCSrc, RegWrite, ALUSrc, MemWrite, ResultSrc;
    output [1:0] ImmSrc;
    output [2:0] ALUControl;

    wire [1:0] ALUOp;
    wire op5, Branch;

    assign op5 = op[5];

    main_decoder main_dec (
        .op(op), .RegWrite(RegWrite), .ALUSrc(ALUSrc), .MemWrite(MemWrite), 
        .ResultSrc(ResultSrc), .Branch(Branch), .ImmSrc(ImmSrc), .ALUOp(ALUOp)
    );

    alu_decoder alu_dec (
        .ALUOp(ALUOp), .func3(func3), .op5(op5), .func7_5(func7), .ALUControl(ALUControl)
    );

    assign PCSrc = zero & Branch;
    
endmodule

lab-07/Instruction-memory/design.v
module instruction_memory(reset,A,RD);

    input[31:0] A;
    input reset;
    output [31:0] RD;

    reg[31:0] mem [1023:0]; // 8 byte // 16 half word // 32 word

    assign RD = (reset == 1'b1) ? 32'h00000000 : mem[A[31:2]];

    initial begin
      // mem[0] <= 32'h00000013;
      // mem[1] <= 32'h0002A203;
      // mem[2] <= 32'h8142A203;
      // addi x10,x10,0
      // lw x6,1(x10)
      // addi x6,x6,3
      mem[0] <= 32'h00050513;
      mem[1] <= 32'h00152303;
      mem[2] <= 32'h00330313;

      // addi x10,x10,0
      // lw x6,1(x10)
      // lw x5,0(x10)
      // add x6,x6,x5
      // mem[0] <= 32'h00050513;
      // mem[1] <= 32'h00152303;
      // mem[2] <= 32'h00052283;
      // mem[3] <= 32'h00530333;

      // mem[1] <= 32'h0002A203;
    end

endmodule

lab-07/PC/design.v
module program_counter(PCNext,clk,reset,PC);

    input[31:0] PCNext;
    output reg[31:0] PC;
    input clk,reset;


    always @(posedge clk) begin
      if(reset == 1'b1) begin
        PC <=32'h00000000;
      end
      else begin
        PC <= PCNext;
      end
    end

endmodule

lab-07/Single_Cycle.v
`include "./PC/design.v"
`include "./Instruction-memory/design.v"
`include "./register-file/design.v"
`include "./ControlUnit/control_unit.v"
`include "./sign-extension/design.v"
`include "./ALU/design.v"
`include "./data-memory/design.v"
`include "./adder/design.v"
`include "./ControlUnit/DecoderModules/main_decoder.v"
`include "./ControlUnit/DecoderModules/alu_decoder.v"


module Single_Cycle(clk,reset);
    input clk,reset;

    // Interim Wire Declaration
        wire [31:0] PC_w;
        wire [31:0] Instruction;
        wire [31:0] RD1;
        wire [31:0] Extended;
        wire [31:0]ALUResult;
        wire RegWrite;
        wire [31:0] RD;
        wire [31:0] NextIns;
        wire [2:0]ALUControl;


    // Module Initialization
    program_counter program_counter (                                   // fetch cycle ==>
                                        .clk(clk),
                                        .reset(reset),
                                        .PC(PC_w),
                                        .PCNext(NextIns)
                                        );

    instruction_memory instruction_memory (
                                            .reset(reset),
                                            .A(PC_w),
                                            .RD(Instruction)
                                            );                          // <==

    control_unit control_unit (                                         // Decoding ==>
                                .zero(),
                                .op(Instruction[6:0]),
                                .func3(Instruction[14:12]),
                                .func7(),
                                .PCSrc(),
                                .RegWrite(RegWrite),
                                .ALUSrc(),
                                .MemWrite(),
                                .ResultSrc(),
                                .ImmSrc(),
                                .ALUControl(ALUControl)
                                );

    register_file register_file (
                                    .A1(Instruction[19:15]),
                                    .A2(),
                                    .A3(Instruction[11:7]),
                                    .clk(clk),
                                    .reset(reset),
                                    .RD1(RD1),
                                    .RD2(),
                                    .WD3(RD),
                                    .WE3(RegWrite)
                                    );

    sign_extension sign_extension (
                                    .Imm(Instruction[31:20]),
                                    .ImmExt(Extended)
                                    );                                  // <==

    Flags_ALU Flags_ALU (
                        .A(RD1),
                        .B(Extended),
                        .ctrl(ALUControl),
                        .Result(ALUResult),
                        .Z(),
                        .N(),
                        .C(),
                        .V()
                        );

    data_memory data_memory (
                                .clk(clk),
                                .A(ALUResult),
                                .WD(),
                                .WE(1'b0),
                                .RD(RD),
                                .reset(reset)
                            );

    Adder Adder(
                .Inp1(PC_w),
                .Inp2(32'd4),
                .Sum(NextIns)
                );
    
endmodule

Lab-09/testBench.v
module tb();

    reg clk=0,reset;

    Single_Cycle dut( 
                       .clk(clk),
                       .reset(reset)
                    );

    always begin 
        clk = ~clk;
        #50;
    end

    initial begin
        reset <= 1'b1;
        #100;
        reset <= 1'b0;
        #500;
        $finish;
    end

    initial begin 
        $dumpfile("dump.vcd");
        $dumpvars(0);
    end


endmodule

lab-07/dump.vcd
$date
	Sun Dec 18 14:00:38 2022
$end
$version
	Icarus Verilog
$end
$timescale
	1s
$end
$scope module tb $end
$var reg 1 ! clk $end
$var reg 1 " reset $end
$scope module dut $end
$var wire 1 ! clk $end
$var wire 1 " reset $end
$var wire 1 # RegWrite $end
$var wire 32 $ RD1 [31:0] $end
$var wire 32 % RD [31:0] $end
$var wire 32 & PC_w [31:0] $end
$var wire 32 ' NextIns [31:0] $end
$var wire 32 ( Instruction [31:0] $end
$var wire 32 ) Extended [31:0] $end
$var wire 32 * ALUResult [31:0] $end
$var wire 3 + ALUControl [2:0] $end
$scope module Adder $end
$var wire 32 , Inp2 [31:0] $end
$var wire 32 - Sum [31:0] $end
$var wire 32 . Inp1 [31:0] $end
$upscope $end
$scope module Flags_ALU $end
$var wire 32 / A_and_B [31:0] $end
$var wire 32 0 A_or_B [31:0] $end
$var wire 32 1 B_not [31:0] $end
$var wire 1 2 C $end
$var wire 1 3 V $end
$var wire 1 4 ctrl1_not $end
$var wire 32 5 not_Result [31:0] $end
$var wire 1 6 xnor_A_B_ctrl0 $end
$var wire 1 7 xor_A_Sum $end
$var wire 3 8 ctrl [2:0] $end
$var wire 1 9 Z $end
$var wire 32 : S1 [31:0] $end
$var wire 32 ; Result [31:0] $end
$var wire 1 < N $end
$var wire 1 = Cout $end
$var wire 32 > B [31:0] $end
$var wire 32 ? A_sum_B [31:0] $end
$var wire 32 @ A [31:0] $end
$upscope $end
$scope module control_unit $end
$var wire 1 A PCSrc $end
$var wire 3 B func3 [2:0] $end
$var wire 1 C func7 $end
$var wire 7 D op [6:0] $end
$var wire 1 E zero $end
$var wire 1 F op5 $end
$var wire 1 G ResultSrc $end
$var wire 1 # RegWrite $end
$var wire 1 H MemWrite $end
$var wire 2 I ImmSrc [1:0] $end
$var wire 1 J Branch $end
$var wire 1 K ALUSrc $end
$var wire 2 L ALUOp [1:0] $end
$var wire 3 M ALUControl [2:0] $end
$scope module alu_dec $end
$var wire 3 N func3 [2:0] $end
$var wire 1 C func7_5 $end
$var wire 1 F op5 $end
$var wire 2 O signal [1:0] $end
$var wire 2 P ALUOp [1:0] $end
$var wire 3 Q ALUControl [2:0] $end
$upscope $end
$scope module main_dec $end
$var wire 7 R op [6:0] $end
$var wire 1 G ResultSrc $end
$var wire 1 # RegWrite $end
$var wire 1 H MemWrite $end
$var wire 2 S ImmSrc [1:0] $end
$var wire 1 J Branch $end
$var wire 1 K ALUSrc $end
$var wire 2 T ALUOp [1:0] $end
$upscope $end
$upscope $end
$scope module data_memory $end
$var wire 32 U A [31:0] $end
$var wire 32 V WD [31:0] $end
$var wire 1 W WE $end
$var wire 1 ! clk $end
$var wire 1 " reset $end
$var wire 32 X RD [31:0] $end
$upscope $end
$scope module instruction_memory $end
$var wire 1 " reset $end
$var wire 32 Y RD [31:0] $end
$var wire 32 Z A [31:0] $end
$upscope $end
$scope module program_counter $end
$var wire 32 [ PCNext [31:0] $end
$var wire 1 ! clk $end
$var wire 1 " reset $end
$var reg 32 \ PC [31:0] $end
$upscope $end
$scope module register_file $end
$var wire 5 ] A1 [4:0] $end
$var wire 5 ^ A2 [4:0] $end
$var wire 5 _ A3 [4:0] $end
$var wire 32 ` WD3 [31:0] $end
$var wire 1 # WE3 $end
$var wire 1 ! clk $end
$var wire 1 " reset $end
$var wire 32 a RD2 [31:0] $end
$var wire 32 b RD1 [31:0] $end
$upscope $end
$scope module sign_extension $end
$var wire 12 c Imm [11:0] $end
$var wire 32 d ImmExt [31:0] $end
$upscope $end
$upscope $end
$upscope $end
$enddefinitions $end
$comment Show the parameter values. $end
$dumpall
$end
#0
$dumpvars
b0 d
b0 c
b0 b
b0 a
b101 `
b0 _
bz ^
b0 ]
bx \
bx [
bx Z
b0 Y
b101 X
0W
bz V
b0 U
b0 T
b0 S
b0 R
b0 Q
b0 P
b0z O
b0 N
b0 M
b0 L
0K
0J
b0 I
0H
0G
0F
zE
b0 D
zC
b0 B
0A
b0 @
b0 ?
b0 >
0=
0<
b0 ;
b0 :
19
b0 8
07
16
b11111111111111111111111111111111 5
14
03
02
b11111111111111111111111111111111 1
b0 0
b0 /
bx .
bx -
b100 ,
b0 +
b0 *
b0 )
b0 (
bx '
bx &
b101 %
b0 $
0#
1"
1!
$end
#50
0!
#100
b1010 _
b1010 ]
b10011 D
b10011 R
b1010000010100010011 (
b1010000010100010011 Y
bx a
b100 '
b100 -
b100 [
b0 &
b0 .
b0 Z
b0 \
0"
1!
#150
0!
#200
b111 %
b111 X
b111 `
09
b11111111111111111111111111111110 5
b1 *
b1 ;
b1 U
b1 ?
1#
1K
b1 :
b11111111111111111111111111111110 1
b1 0
1G
b1 )
b1 >
b1 d
b1 c
b110 _
b10 B
b10 N
b11 D
b11 R
b101010010001100000011 (
b101010010001100000011 Y
b1000 '
b1000 -
b1000 [
b100 &
b100 .
b100 Z
b100 \
1!
#250
0!
#300
b101 %
b101 X
b101 `
19
b11111111111111111111111111111111 5
b0 *
b0 ;
b0 U
b0 ?
b0 :
b11111111111111111111111111111111 1
b0 0
b0 )
b0 >
b0 d
b0 c
b101 _
b1010010001010000011 (
b1010010001010000011 Y
b1100 '
b1100 -
b1100 [
b1000 &
b1000 .
b1000 Z
b1000 \
1!
#350
0!
#400
x3
x7
x6
x<
x2
x=
b0x +
b0x 8
b0x M
b0x Q
bx %
bx X
bx `
x9
bx 5
bx *
bx ;
bx U
bx ?
0K
bx :
b11111111111111111111111111111010 1
b111 0
b101 /
b111 $
b111 @
b111 b
b1z O
1F
0G
b10 L
b10 P
b10 T
b101 )
b101 >
b101 d
b101 c
b110 _
b110 ]
b0 B
b0 N
b110011 D
b110011 R
b10100110000001100110011 (
b10100110000001100110011 Y
b10000 '
b10000 -
b10000 [
b1100 &
b1100 .
b1100 Z
b1100 \
1!
#450
bx1x1 0
b0x0x /
bx $
bx @
bx b
0!
#500
x4
bx +
bx 8
bx M
bx Q
x#
xK
xA
bx 1
bx 0
bx /
bxz O
xF
xH
xG
xJ
bx I
bx S
bx L
bx P
bx T
bx )
bx >
bx d
bx c
bx _
bx ]
bx B
bx N
bx D
bx R
bx (
bx Y
b10100 '
b10100 -
b10100 [
b10000 &
b10000 .
b10000 Z
b10000 \
1!
#550
0!
#600
b11000 '
b11000 -
b11000 [
b10100 &
b10100 .
b10100 Z
b10100 \
1!
